ServiceGateway/__init__.py
ServiceGateway/__meta__.py
ServiceGateway/exceptions.py
ServiceGateway/rest_api.py
ServiceGateway/rubber.py
ServiceGateway/templates/service/home.html
ServiceGateway-1.9.2.dist-info/AUTHORS.rst
ServiceGateway-1.9.2.dist-info/LICENSE
ServiceGateway-1.9.2.dist-info/METADATA
ServiceGateway-1.9.2.dist-info/WHEEL
ServiceGateway-1.9.2.dist-info/entry_points.txt
ServiceGateway-1.9.2.dist-info/top_level.txt
ServiceGateway-1.9.2.dist-info/RECORD
