Metadata-Version: 2.1
Name: ServiceGateway
Version: 1.9.2
Summary: This package offers a HTTP REST API to a distributed service queue Service Gateway (SG).
Home-page: http://www.crim.ca
Author: osterrfr@crim.ca
Author-email: vesta-support@crim.ca
License: copyright CRIM 2015
Keywords: CANARIE,LoadBalancing,Services
Platform: linux-x86_64
Classifier: Natural Language :: English
Classifier: Programming Language :: Python :: 2
Classifier: Programming Language :: Python :: 2.7
Requires-Dist: python-novaclient (==2.23.2)
Requires-Dist: VestaRestPackage (==1.9.3)
